dispel4py/__init__.py
dispel4py/__main__.py
dispel4py/base.py
dispel4py/core.py
dispel4py/utils.py
dispel4py/visualisation.py
dispel4py/workflow_graph.py
dispel4py/examples/__init__.py
dispel4py/examples/wordcount.py
dispel4py/examples/graph_testing/__init__.py
dispel4py/examples/graph_testing/delayed_pipeline.py
dispel4py/examples/graph_testing/group_by.py
dispel4py/examples/graph_testing/grouping_alltoone.py
dispel4py/examples/graph_testing/grouping_onetoall.py
dispel4py/examples/graph_testing/grouping_split_merge.py
dispel4py/examples/graph_testing/large_teecopy.py
dispel4py/examples/graph_testing/loopcopy.py
dispel4py/examples/graph_testing/multi_producer.py
dispel4py/examples/graph_testing/parallel_pipeline.py
dispel4py/examples/graph_testing/partition_parallel_pipeline.py
dispel4py/examples/graph_testing/pipeline_composite.py
dispel4py/examples/graph_testing/pipeline_test.py
dispel4py/examples/graph_testing/producer_tee.py
dispel4py/examples/graph_testing/sieveoferatosthenes.py
dispel4py/examples/graph_testing/split_merge.py
dispel4py/examples/graph_testing/teecopy.py
dispel4py/examples/graph_testing/testing_PEs.py
dispel4py/examples/graph_testing/unconnected_pipeline.py
dispel4py/examples/graph_testing/word_count.py
dispel4py/examples/graph_testing/word_count_filter.py
dispel4py/new/__init__.py
dispel4py/new/aggregate.py
dispel4py/new/aggregate_test.py
dispel4py/new/mappings.py
dispel4py/new/monitoring.py
dispel4py/new/mpi_process.py
dispel4py/new/mpi_process_test.py
dispel4py/new/mpi_queue_process.py
dispel4py/new/multi_process.py
dispel4py/new/processor.py
dispel4py/new/simple_process.py
dispel4py/new/spark_process.py
dispel4py/storm/__init__.py
dispel4py/storm/client.py
dispel4py/storm/storm_submission.py
dispel4py/storm/storm_submission_client.py
dispel4py/storm/topology.py
dispel4py/storm/utils.py
dispel4py-1.2.1.dist-info/DESCRIPTION.rst
dispel4py-1.2.1.dist-info/entry_points.txt
dispel4py-1.2.1.dist-info/METADATA
dispel4py-1.2.1.dist-info/metadata.json
dispel4py-1.2.1.dist-info/RECORD
dispel4py-1.2.1.dist-info/top_level.txt
dispel4py-1.2.1.dist-info/WHEEL
