Metadata-Version: 2.0
Name: dispel4py
Version: 1.2.1
Summary: dispel4py is a free and open-source Python library for         describing abstract stream-based workflows for distributed         data-intensive applications.
Home-page: http://dispel4py.org
Author: The University of Edinburgh
Author-email: a.krause@epcc.ed.ac.uk
License: Apache 2
Keywords: dispel4py dispel workflows processing elements data intensive
Platform: UNKNOWN
Classifier: Development Status :: 4 - Beta
Classifier: Topic :: Utilities
Classifier: License :: OSI Approved :: Apache 2 License
Requires-Dist: networkx
Requires-Dist: flake8
